ibm_cos_fs/__init__.py
ibm_cos_fs/bucket_tree.py
ibm_cos_fs/bucket_tree_node.py
ibm_cos_fs/test_cos_fs.py
ibm_cos_simple_fs-0.0.8.dist-info/METADATA
ibm_cos_simple_fs-0.0.8.dist-info/RECORD
ibm_cos_simple_fs-0.0.8.dist-info/WHEEL
ibm_cos_simple_fs-0.0.8.dist-info/top_level.txt
