Metadata-Version: 2.1
Name: ibm-cos-simple-fs
Version: 0.0.8
Summary: A package for representing IBM Cloud Object Storage (COS) bucket like a file system.
Home-page: https://github.com/psyking841/ibm-cos-simple-fs
Author: Shengyi Pan
Author-email: shengyi.pan1@gmail.com
License: UNKNOWN
Platform: UNKNOWN
Classifier: Programming Language :: Python :: 3
Classifier: License :: OSI Approved :: Apache Software License
Classifier: Operating System :: OS Independent
